mashpit/__init__.py
mashpit/build.py
mashpit/mashpit.py
mashpit/query.py
mashpit/update.py
mashpit-0.9.41.dist-info/LICENSE
mashpit-0.9.41.dist-info/METADATA
mashpit-0.9.41.dist-info/WHEEL
mashpit-0.9.41.dist-info/entry_points.txt
mashpit-0.9.41.dist-info/top_level.txt
mashpit-0.9.41.dist-info/RECORD
