Metadata-Version: 2.1
Name: mashpit
Version: 0.9.41
Summary: A sketch-based surveillance platform
Home-page: https://github.com/tongzhouxu/mashpit
Author: Tongzhou Xu
Author-email: tongzhou.xu@uga.edu
License-File: LICENSE
Requires-Dist: sourmash ~=4.6.1
Requires-Dist: ncbi-datasets-pylib ~=14.6.2
Requires-Dist: pandas
Requires-Dist: biopython
Requires-Dist: scikit-bio
Requires-Dist: tqdm
Requires-Dist: flask
Requires-Dist: dask[dataframe]
